<?xml version='1.0' encoding='utf-8'?>
<entry xmlns="http://www.w3.org/2005/Atom" xmlns:m="http://schemas.microsoft.com/ado/2007/08/dataservices/metadata" xmlns:d="http://schemas.microsoft.com/ado/2007/08/dataservices" xml:base="https://l251267-tmn.hci.us3.hana.ondemand.com:443/itspaces/odata/1.0/workspace.svc/">
  <id>https://l251267-tmn.hci.us3.hana.ondemand.com:443/itspaces/odata/1.0/workspace.svc/ContentPackages('SDSalesOrders')</id>
  <title type="text">ContentPackages</title>
  <updated>2021-05-13T04:25:04.724Z</updated>
  <category term="ContentPackageModel.ContentPackage" scheme="http://schemas.microsoft.com/ado/2007/08/dataservices/scheme"/>
  <link href="ContentPackages('SDSalesOrders')" rel="edit" title="ContentPackage"/>
  <link href="ContentPackages('SDSalesOrders')/Artifacts" rel="http://schemas.microsoft.com/ado/2007/08/dataservices/related/Artifacts" title="Artifacts" type="application/atom+xml;type=feed"/>
  <link href="ContentPackages('SDSalesOrders')/Files" rel="http://schemas.microsoft.com/ado/2007/08/dataservices/related/Files" title="Files" type="application/atom+xml;type=feed"/>
  <link href="ContentPackages('SDSalesOrders')/Urls" rel="http://schemas.microsoft.com/ado/2007/08/dataservices/related/Urls" title="Urls" type="application/atom+xml;type=feed"/>
  <link href="ContentPackages('SDSalesOrders')/MediaLinks" rel="http://schemas.microsoft.com/ado/2007/08/dataservices/related/MediaLinks" title="MediaLinks" type="application/atom+xml;type=feed"/>
  <content type="application/xml">
    <m:properties>
      <d:TechnicalName>SDSalesOrders</d:TechnicalName>
      <d:DisplayName>I-001 Magento SAP Integration</d:DisplayName>
      <d:ShortText>Interaction between Magento and S4HANA-Sales orders Creation-Update Inventory from S4Hana to Magento-Update Order status-Update Invoice Url</d:ShortText>
      <d:reg_id>d7eeec3eb7e340a29c16dab4b1458e59</d:reg_id>
      <d:Featured m:null="true"/>
      <d:Scope m:null="true"/>
      <d:Description>&lt;p&gt;&lt;/p&gt;&lt;p&gt;&lt;/p&gt;&lt;p&gt;&lt;/p&gt;&lt;p&gt;&lt;/p&gt;&lt;p&gt;&lt;/p&gt;&lt;p&gt;&lt;/p&gt;&lt;p&gt;&lt;/p&gt;&lt;p&gt;&lt;/p&gt;&lt;p&gt;&lt;/p&gt;&lt;p&gt;&lt;/p&gt;&lt;p&gt;&lt;/p&gt;&lt;p&gt;&lt;/p&gt;&lt;p&gt;&lt;/p&gt;</d:Description>
      <d:Version>2.0</d:Version>
      <d:Category>Integration</d:Category>
      <d:Mode>EDIT_ALLOWED</d:Mode>
      <d:Vendor m:null="true"/>
      <d:OrgName m:null="true"/>
      <d:SupportedPlatforms>SAP HANA Cloud Integration</d:SupportedPlatforms>
      <d:Products m:null="true"/>
      <d:Industries m:null="true"/>
      <d:LineOfBusiness m:null="true"/>
      <d:Keywords m:null="true"/>
      <d:Countries m:null="true"/>
      <d:AvgRating>0.0</d:AvgRating>
      <d:RatingCount>0</d:RatingCount>
      <d:PublishedAt m:null="true"/>
      <d:PublishedBy m:null="true"/>
      <d:CreatedAt>2021-05-06T23:13:42.27</d:CreatedAt>
      <d:CreatedBy>S0020964931</d:CreatedBy>
      <d:ModifiedAt>2021-05-06T23:13:42.276</d:ModifiedAt>
      <d:ModifiedBy>S0020964931</d:ModifiedBy>
      <d:PartnerContent m:null="true"/>
      <d:CertifiedBySap m:null="true"/>
      <d:AdditionalAttributes m:null="true"/>
    </m:properties>
  </content>
</entry>
